akamai_storage/__init__.py
akamai_storage/admin.py
akamai_storage/models.py
akamai_storage/storage.py
akamai_storage/tests.py
akamai_storage/utils.py
akamai_storage/views.py
akamai_storage/db/__init__.py
akamai_storage/db/fields.py
akamai_storage/forms/__init__.py
akamai_storage/forms/fields.py
akamai_storage/forms/models.py
akamai_storage/migrations/__init__.py
django_akamai_storage-20141026.1.dist-info/DESCRIPTION.rst
django_akamai_storage-20141026.1.dist-info/METADATA
django_akamai_storage-20141026.1.dist-info/metadata.json
django_akamai_storage-20141026.1.dist-info/RECORD
django_akamai_storage-20141026.1.dist-info/top_level.txt
django_akamai_storage-20141026.1.dist-info/WHEEL
