Metadata-Version: 2.0
Name: django-akamai-storage
Version: 20141026.1
Summary: Django storage engine that connects to Akamai NetStorage.
Home-page: https://github.com/g3rd/django-akamai-storage
Author: Chad Shryock
Author-email: chad@g3rdmedia.com
License: MIT License (MIT)
Download-URL: https://github.com/g3rd/django-akamai-storage/zipball/master
Platform: UNKNOWN
Classifier: Development Status :: 3 - Alpha
Classifier: Environment :: Web Environment
Classifier: Framework :: Django
Classifier: Intended Audience :: Developers
Classifier: License :: OSI Approved :: MIT License
Classifier: Operating System :: OS Independent
Classifier: Programming Language :: Python
Classifier: Programming Language :: Python :: 2.7
Classifier: Programming Language :: Python :: 3.3
Classifier: Topic :: Internet :: WWW/HTTP
Classifier: Topic :: Internet :: WWW/HTTP :: Dynamic Content
Classifier: Topic :: Software Development :: Libraries :: Application Frameworks
Classifier: Topic :: Software Development :: Libraries :: Python Modules
Requires: Django (>=1.7)
Requires-Dist: django-polymorphic (>=0.5.6)
